automatix/__init__.py
automatix/automatix.py
automatix/automatix_test.py
automatix/bash_completion.py
automatix/batch_runner.py
automatix/bundlewrap.py
automatix/colors.py
automatix/command.py
automatix/command_test.py
automatix/config.py
automatix/config_test.py
automatix/environment.py
automatix/environment_test.py
automatix/helpers.py
automatix/logger.py
automatix/parallel.py
automatix/parallel_runner.py
automatix/parallel_ui.py
automatix/progress_bar.py
automatix-3.2.0.dist-info/licenses/LICENSE
automatix-3.2.0.dist-info/METADATA
automatix-3.2.0.dist-info/WHEEL
automatix-3.2.0.dist-info/entry_points.txt
automatix-3.2.0.dist-info/top_level.txt
automatix-3.2.0.dist-info/RECORD
