Metadata-Version: 2.4
Name: automatix
Version: 3.2.0
Summary: Automation wrapper for bash and python commands
Home-page: https://github.com/seibert-media/automatix
Author: Johannes Paul
Author-email: johannes.paul@seibert.group, vanadinit@quantentunnel.de
License: MIT
Keywords: bash,shell,command,automation,process,wrapper,devops,system administration
Classifier: Programming Language :: Python :: 3
Classifier: License :: OSI Approved :: MIT License
Requires-Python: >=3.10
License-File: LICENSE
Requires-Dist: pyyaml>=5.1
Provides-Extra: tests
Requires-Dist: cython<3.0.0; extra == "tests"
Requires-Dist: pytest; extra == "tests"
Requires-Dist: pytest-docker; extra == "tests"
Requires-Dist: flake8; extra == "tests"
Provides-Extra: bash-completion
Requires-Dist: argcomplete; extra == "bash-completion"
Dynamic: author
Dynamic: author-email
Dynamic: classifier
Dynamic: description
Dynamic: description-content-type
Dynamic: home-page
Dynamic: keywords
Dynamic: license
Dynamic: license-file
Dynamic: provides-extra
Dynamic: requires-dist
Dynamic: requires-python
Dynamic: summary
